gamepandas/__init__.py
gamepandas/gameframes.py
gamepandas/utils.py
gamepandas-0.0.3.dist-info/METADATA
gamepandas-0.0.3.dist-info/WHEEL
gamepandas-0.0.3.dist-info/top_level.txt
gamepandas-0.0.3.dist-info/RECORD
